setup.py
helloname/__init__.py
helloname.egg-info/PKG-INFO
helloname.egg-info/SOURCES.txt
helloname.egg-info/dependency_links.txt
helloname.egg-info/not-zip-safe
helloname.egg-info/top_level.txt