Metadata-Version: 1.0
Name: helloname
Version: 0.2
Summary: Just call you by name
Home-page: http://none
Author: me
Author-email: itsreallyme@bmstu.ru
License: GPL
Platform: UNKNOWN
